.bumbversion.cfg
MANIFEST.in
README.md
requirements.txt
setup.py
src/DecentLogs_z6.egg-info/PKG-INFO
src/DecentLogs_z6.egg-info/SOURCES.txt
src/DecentLogs_z6.egg-info/dependency_links.txt
src/DecentLogs_z6.egg-info/entry_points.txt
src/DecentLogs_z6.egg-info/not-zip-safe
src/DecentLogs_z6.egg-info/requires.txt
src/DecentLogs_z6.egg-info/top_level.txt
src/decent_logs/__init__.py
src/decent_logs/log_record.py
src/decent_logs/withinternallog.py