Metadata-Version: 1.1
Name: DecentLogs-z6
Version: 6.0.0
Summary:  Simple library to have objects keeping their log messages. 
Home-page: http://github.com/AndreaCensi/decent_logs
Author: Andrea Censi
Author-email: UNKNOWN
License: UNKNOWN
Download-URL: http://github.com/AndreaCensi/decent_logs/tarball/6.0.0
Platform: UNKNOWN
Classifier: Development Status :: 4 - Beta
